MANIFEST.in
README.rst
setup.py
docs/HISTORY.rst
docs/INSTALL.txt
docs/LICENSE.GPL
docs/LICENSE.txt
src/rt/__init__.py
src/rt.zptformfield.egg-info/PKG-INFO
src/rt.zptformfield.egg-info/SOURCES.txt
src/rt.zptformfield.egg-info/dependency_links.txt
src/rt.zptformfield.egg-info/entry_points.txt
src/rt.zptformfield.egg-info/namespace_packages.txt
src/rt.zptformfield.egg-info/not-zip-safe
src/rt.zptformfield.egg-info/requires.txt
src/rt.zptformfield.egg-info/top_level.txt
src/rt/zptformfield/__init__.py
src/rt/zptformfield/autocomplete_lines.py
src/rt/zptformfield/base.py
src/rt/zptformfield/configure.zcml
src/rt/zptformfield/lines.py
src/rt/zptformfield/tests.zcml
src/rt/zptformfield/javascript/autocomplete_lines.js
src/rt/zptformfield/javascript/lines.js
src/rt/zptformfield/javascript/reference.js
src/rt/zptformfield/locales/rebuildPo.sh
src/rt/zptformfield/locales/rt.zptformfield.pot
src/rt/zptformfield/locales/it/LC_MESSAGES/rt.zptformfield.po
src/rt/zptformfield/resources/delete.png
src/rt/zptformfield/templates/autocomplete_lines.pt
src/rt/zptformfield/templates/base_lines.pt
src/rt/zptformfield/templates/calendar.pt
src/rt/zptformfield/templates/lines.pt
src/rt/zptformfield/templates/multivalued_reference.pt
src/rt/zptformfield/templates/reference.pt
src/rt/zptformfield/templates/tinymce.pt
src/rt/zptformfield/tests/__init__.py
src/rt/zptformfield/tests/autocomplete_lines.pt
src/rt/zptformfield/tests/calendar.pt
src/rt/zptformfield/tests/configure.zcml
src/rt/zptformfield/tests/extender.py
src/rt/zptformfield/tests/lines.pt
src/rt/zptformfield/tests/multivalued_reference.pt
src/rt/zptformfield/tests/reference.pt
src/rt/zptformfield/tests/tinymce.pt
src/rt/zptformfield/tests/view.py