Metadata-Version: 1.0
Name: rt.zptformfield
Version: 0.2.1
Summary: Some ZPT macros for Zope/Plone HTML forms development
Home-page: http://github.com/RedTurtle/rt.zptformfield
Author: RedTurtle Technology
Author-email: sviluppoplone@redturtle.it
License: GPL
Keywords: plone zpt zope form macro
Platform: UNKNOWN
Classifier: Development Status :: 4 - Beta
Classifier: Framework :: Plone
Classifier: Framework :: Plone :: 4.0
Classifier: Framework :: Plone :: 4.1
Classifier: Framework :: Plone :: 4.2
Classifier: Framework :: Plone :: 4.3
Classifier: Framework :: Zope2
Classifier: Programming Language :: Python
Classifier: Intended Audience :: Developers
